langevin_sampling/SGLD.py
langevin_sampling/__init__.py
langevin_sampling/precondSGLD.py
langevin_sampling/samplers.py
langevin_sampling-1.4.dist-info/LICENSE
langevin_sampling-1.4.dist-info/METADATA
langevin_sampling-1.4.dist-info/WHEEL
langevin_sampling-1.4.dist-info/top_level.txt
langevin_sampling-1.4.dist-info/RECORD
