Metadata-Version: 2.1
Name: langevin_sampling
Version: 1.4
Summary: Sampling with gradient-based Markov Chain Monte Carlo approaches
Home-page: https://github.com/alisiahkoohi/Langevin-dynamics
Author: Ali Siahkoohi
Author-email: ali.siahkoohi@gmail.com
Classifier: Programming Language :: Python :: 3
Classifier: License :: OSI Approved :: MIT License
Classifier: Operating System :: OS Independent
Requires-Python: >=3.6
License-File: LICENSE
Requires-Dist: torch
Requires-Dist: matplotlib
Requires-Dist: numpy
Requires-Dist: tqdm
Requires-Dist: rosenbrock
